Flask_Caching_IceFruit-0.0.3.dist-info/METADATA
Flask_Caching_IceFruit-0.0.3.dist-info/RECORD
Flask_Caching_IceFruit-0.0.3.dist-info/WHEEL
Flask_Caching_IceFruit-0.0.3.dist-info/top_level.txt
flask_caching/__init__.py
flask_caching/_compat.py
flask_caching/jinja2ext.py
flask_caching/backends/__init__.py
flask_caching/backends/backends.py
flask_caching/backends/cache.py
flask_caching/backends/clients.py
